MANIFEST.in
Pipfile
README.md
requirements.txt
setup.py
custom_redis/__init__.py
custom_redis.egg-info/PKG-INFO
custom_redis.egg-info/SOURCES.txt
custom_redis.egg-info/dependency_links.txt
custom_redis.egg-info/entry_points.txt
custom_redis.egg-info/top_level.txt
custom_redis.egg-info/zip-safe
custom_redis/client/__init__.py
custom_redis/client/errors.py
custom_redis/client/functions.py
custom_redis/client/redis.py
custom_redis/client/utils.py
custom_redis/server/__init__.py
custom_redis/server/bases.py
custom_redis/server/data_types.py
custom_redis/server/errors.py
custom_redis/server/redis_command.py
custom_redis/server/redis_server.py
custom_redis/server/sorted_dict.py
custom_redis/server/utils.py
custom_redis/server/zset.py