Metadata-Version: 2.1
Name: custom-redis
Version: 3.2.2
Summary: python实现简单redis，实现redis基本功能以及可插拔数据结构。 
Home-page: https://www.github.com/ShichaoMa/custom_redis
Author: cn
Author-email: 308299269@foxmail.com
License: MIT
Keywords: custom redis
Platform: UNKNOWN
Classifier: License :: OSI Approved :: MIT License
Classifier: Programming Language :: Python :: 3
Classifier: Intended Audience :: Developers
Classifier: Operating System :: Unix
